.gitignore
COPYING.LESSER.txt
README.rst
setup.py
score/__init__.py
score.uwsgi.egg-info/PKG-INFO
score.uwsgi.egg-info/SOURCES.txt
score.uwsgi.egg-info/dependency_links.txt
score.uwsgi.egg-info/entry_points.txt
score.uwsgi.egg-info/namespace_packages.txt
score.uwsgi.egg-info/not-zip-safe
score.uwsgi.egg-info/requires.txt
score.uwsgi.egg-info/top_level.txt
score/uwsgi/__init__.py
score/uwsgi/cli.py
score/uwsgi/iniparser.py
score/uwsgi/process.py