Metadata-Version: 1.1
Name: score.uwsgi
Version: 0.1.3
Summary: Management of uwsgi processes for The SCORE Framework
Home-page: http://strg.at
Author: strg.at
Author-email: support@strg.at
License: LGPL
Keywords: web wsgi uwsgi
Platform: UNKNOWN
Classifier: Development Status :: 3 - Alpha
Classifier: Environment :: Console
Classifier: Environment :: Web Environment
Classifier: Intended Audience :: Developers
Classifier: License :: OSI Approved :: GNU Lesser General Public License v3 or later (LGPLv3+)
Classifier: Operating System :: OS Independent
Classifier: Programming Language :: SQL
Classifier: Programming Language :: Python :: 3
Classifier: Programming Language :: Python :: 3.4
Classifier: Programming Language :: Python :: 3.5
Classifier: Topic :: Software Development :: Libraries :: Application Frameworks
